{
  "status": "pass",
  "check_count": 11,
  "scope": "statistical robustness audit for probability, exact-collision, sensitivity, and resampling outputs",
  "checks": [
    {
      "check": "historical empirical upper bound",
      "expected": "51 governor contests and historical maximum 3 repeated pairs",
      "actual": "51 contests, max 3",
      "status": "pass"
    },
    {
      "check": "Poisson baseline probability",
      "expected": "P(C>=5) equals 0.0011484064248148407",
      "actual": "0.0011484064248148407",
      "status": "pass"
    },
    {
      "check": "exact collision probability",
      "expected": "exact P(C>=5) equals 0.0012190883791786122",
      "actual": "0.0012190883791786122",
      "status": "pass"
    },
    {
      "check": "Poisson and exact agreement",
      "expected": "absolute difference below 0.0001",
      "actual": "diff 7.068195436377156e-05",
      "status": "pass"
    },
    {
      "check": "pre-designated five-pair conditional probability",
      "expected": "P equals (1/K)^5 = 9.540700009422666e-26 for five designated pairs",
      "actual": "9.540700009422666e-26",
      "status": "pass"
    },
    {
      "check": "nonparametric resampling threshold 5",
      "expected": "0 exceedances in 200,000 trials",
      "actual": "0 exceedances in 200000 trials",
      "status": "pass"
    },
    {
      "check": "rule-of-three upper bound",
      "expected": "95% upper bound equals 0.000015",
      "actual": "1.5e-05",
      "status": "pass"
    },
    {
      "check": "effective-pair-space sensitivity",
      "expected": "K=50,000 remains below 2.1%, baseline below 0.12%, K=200,000 below 0.006%",
      "actual": "K50 0.02054999234891819, baseline 0.0011484064248148407, K200 5.130716523893408e-05",
      "status": "pass"
    },
    {
      "check": "K sensitivity monotonicity",
      "expected": "probability decreases as K increases",
      "actual": "K50 0.02054999234891819, baseline 0.0011484064248148407, K200 5.130716523893408e-05",
      "status": "pass"
    },
    {
      "check": "counting-unit N sensitivity",
      "expected": "probability increases with N but stays below 0.37% through N=450",
      "actual": "N350 0.0004096177139301105, N393 0.0011484064248148407, N450 0.003672039591659959",
      "status": "pass"
    },
    {
      "check": "N sensitivity upper range",
      "expected": "all reported N-sensitivity probabilities for threshold 5 below 0.4%",
      "actual": "max 0.003672039591659959",
      "status": "pass"
    }
  ]
}
